ffstreamer/__init__.py
ffstreamer/__main__.py
ffstreamer/arguments.py
ffstreamer/entrypoint.py
ffstreamer/aio/__init__.py
ffstreamer/aio/stream.py
ffstreamer/apps/__init__.py
ffstreamer/apps/files.py
ffstreamer/apps/inspect.py
ffstreamer/apps/modules.py
ffstreamer/apps/pixels.py
ffstreamer/apps/run.py
ffstreamer/argparse/__init__.py
ffstreamer/argparse/argument_utils.py
ffstreamer/argparse/namespace_utils.py
ffstreamer/argparse/typing_namespace.py
ffstreamer/assets/__init__.py
ffstreamer/chrono/__init__.py
ffstreamer/chrono/datetime.py
ffstreamer/ffmpeg/__init__.py
ffstreamer/ffmpeg/ffmpeg.py
ffstreamer/ffmpeg/ffmpeg_process.py
ffstreamer/ffmpeg/ffmpeg_receiver.py
ffstreamer/ffmpeg/ffmpeg_sender.py
ffstreamer/ffmpeg/ffprobe.py
ffstreamer/ffmpeg/static_lib.py
ffstreamer/inspect/__init__.py
ffstreamer/inspect/type_origin.py
ffstreamer/logging/__init__.py
ffstreamer/logging/colored_formatter.py
ffstreamer/logging/logging.py
ffstreamer/memory/__init__.py
ffstreamer/memory/shared_memory_queue.py
ffstreamer/memory/shared_memory_utils.py
ffstreamer/memory/shared_memory_validator.py
ffstreamer/module/__init__.py
ffstreamer/module/errors.py
ffstreamer/module/module.py
ffstreamer/module/module_printer.py
ffstreamer/module/variables.py
ffstreamer/module/defaults/__init__.py
ffstreamer/module/defaults/bytes2numpy.py
ffstreamer/module/defaults/grayscale.py
ffstreamer/module/defaults/numpy2bytes.py
ffstreamer/module/mixin/__init__.py
ffstreamer/module/mixin/_module_base.py
ffstreamer/module/mixin/module_doc.py
ffstreamer/module/mixin/module_frame.py
ffstreamer/module/mixin/module_open.py
ffstreamer/module/mixin/module_version.py
ffstreamer/network/__init__.py
ffstreamer/network/address_family.py
ffstreamer/package/__init__.py
ffstreamer/package/package_utils.py
ffstreamer/parse/__init__.py
ffstreamer/parse/cfg_parse.py
ffstreamer/parse/env_parse.py
ffstreamer/regex/__init__.py
ffstreamer/regex/access_filter.py
ffstreamer/system/__init__.py
ffstreamer/system/environ.py
ffstreamer-1.0.1.dist-info/LICENSE
ffstreamer-1.0.1.dist-info/METADATA
ffstreamer-1.0.1.dist-info/WHEEL
ffstreamer-1.0.1.dist-info/entry_points.txt
ffstreamer-1.0.1.dist-info/top_level.txt
ffstreamer-1.0.1.dist-info/RECORD
