Metadata-Version: 2.1
Name: ffstreamer
Version: 1.0.1
Summary: FFmpeg Streamer
Home-page: https://github.com/osom8979/ffstreamer
Author: zer0
Author-email: osom8979@gmail.com
Maintainer: zer0
Maintainer-email: osom8979@gmail.com
License: MIT License
Project-URL: GitHub: issues, https://github.com/osom8979/ffstreamer/issues
Project-URL: GitHub: repo, https://github.com/osom8979/ffstreamer
Platform: UNKNOWN
Classifier: Development Status :: 4 - Beta
Classifier: Framework :: AsyncIO
Classifier: Intended Audience :: Developers
Classifier: Operating System :: OS Independent
Classifier: Programming Language :: Python
Classifier: Programming Language :: Python :: 3.9
Classifier: Programming Language :: Python :: 3.10
Classifier: Programming Language :: Python :: 3.11
Classifier: Topic :: Software Development
Classifier: Topic :: Utilities
Classifier: License :: OSI Approved :: MIT License
Requires-Python: >=3.9
License-File: LICENSE
Requires-Dist: coloredlogs
Requires-Dist: static-ffmpeg
Requires-Dist: numpy
Requires-Dist: uvloop
